mic/__init__.py
mic/image_transfer.py
mic/solver.py
mic/utils.py
micg/__init__.py
micg/image_transfer.py
micg/solver.py
micg/utils.py
micg-1.1.0.dist-info/LICENSE
micg-1.1.0.dist-info/METADATA
micg-1.1.0.dist-info/WHEEL
micg-1.1.0.dist-info/entry_points.txt
micg-1.1.0.dist-info/top_level.txt
micg-1.1.0.dist-info/RECORD
